mad_notifications/__init__.py
mad_notifications/admin.py
mad_notifications/apps.py
mad_notifications/models.py
mad_notifications/tests.py
mad_notifications/utils.py
mad_notifications/api/serializers.py
mad_notifications/api/urls.py
mad_notifications/api/views.py
mad_notifications-0.1.6.dist-info/METADATA
mad_notifications-0.1.6.dist-info/WHEEL
mad_notifications-0.1.6.dist-info/top_level.txt
mad_notifications-0.1.6.dist-info/RECORD
