Metadata-Version: 2.1
Name: mad-notifications
Version: 0.1.6
Summary: A Django app to send push notifications to to users.
Home-page: https://www.madithouse.com/
Author: Haseeb Ur Rehman
Author-email: haseeb@madithouse.com
License: BSD-3-Clause  # Example license
Platform: UNKNOWN
Classifier: Environment :: Web Environment
Classifier: Framework :: Django
Classifier: Framework :: Django :: 3.1
Classifier: Intended Audience :: Developers
Classifier: License :: OSI Approved :: BSD License
Classifier: Operating System :: OS Independent
Classifier: Programming Language :: Python
Classifier: Programming Language :: Python :: 3
Classifier: Programming Language :: Python :: 3 :: Only
Classifier: Programming Language :: Python :: 3.6
Classifier: Programming Language :: Python :: 3.7
Classifier: Programming Language :: Python :: 3.8
Classifier: Topic :: Internet :: WWW/HTTP
Classifier: Topic :: Internet :: WWW/HTTP :: Dynamic Content
Requires-Python: >=3.6
Requires-Dist: django (==3.1.0)
Requires-Dist: djangorestframework (==3.12.2)
Requires-Dist: firebase-admin (==5.0.1)
Requires-Dist: google-api-core (==1.31.0)
Requires-Dist: google-auth (==1.33.0)
Requires-Dist: google-auth-httplib2 (==0.1.0)
Requires-Dist: google-api-python-client (==2.13.0)
Requires-Dist: google-cloud-firestore (==2.1.3)
Requires-Dist: googleapis-common-protos (==1.53.0)
